DataFlowModelling/FA_carryLookAhead/carryLookAhead.v
module carryLookAhead(
    cout,sum,a,b,cin
);

input [3:0]a,b;
input cin;
output [3:0]sum;
output cout;

wire [3:0]p;
wire [3:0]g;
wire c1,c2,c3,c4;

//Propagation value = P(i) = A(i) (+) B(i)
assign p[0] = a[0] ^ b[0],p[1] = a[1] ^ b[1],p[2] = a[2] ^ b[2],p[3] = a[3] ^ b[3];

//Generation value = G(i) = A(i).B(i)
assign g[0] = a[0] & b[0],g[1] = a[1] & b[1],g[2] = a[2] & b[2],g[3] = a[3] & b[3];

//Look ahead values

assign c1 = (g[0] | (p[0] & cin)),c2 = (g[1] | (p[1] & (g[0] | (p[0] & cin)))), c3 = (g[2] | (p[2] & (g[1] | (p[1] & (g[0] | (p[0] & cin)))))), c4 = (g[3] | (p[3] & (g[2] | (p[2] & (g[1] | (p[1] & (g[0] | (p[0] & cin))))))));


//Sum value = S(i) = P(i) (+) C(i-1)
assign sum[0] = p[0] ^ cin,sum[1] = p[1] ^ c1,sum[2] = p[2] ^ c2,sum[3] = p[3] ^ c3;

//Carry 
assign cout = c4;


    
endmodule

DataFlowModelling/FA_carryLookAhead/carryLookAhead_tb.v
`timescale 1ps/1ps
`include "carryLookAhead.v"

module carryLookAhead_tb();

reg CIN;
reg [3:0]A,B;
wire COUT;
wire [3:0]SUM;

carryLookAhead uut(.cout (COUT),.sum (SUM),.a (A),.b (B),.cin (CIN));

initial begin
    $dumpfile("CarryLH.vcd");
    $dumpvars(0,carryLookAhead_tb);
    $monitor($time,"\tCin=%b,A=%b,B=%b,SUM=%b,Cout=%b",CIN,A,B,SUM,COUT);

    //carry in = 1
    CIN = 1;
    A=4'd3; B=4'd4;
    #10 A=4'd2; B=4'd5;
    #10 A=4'd9; B=4'd9;
    #10 A=4'd10; B=4'd15;

    //Carry In = A
    #5 CIN = 0;
    #10 A=4'd3; B=4'd4;
    #10 A=4'd2; B=4'd5;
    #10 A=4'd9; B=4'd9;
    #10 A=4'd10; B=4'd15;
end

endmodule

DataFlowModelling/FA_carryLookAhead/CarryLH.vcd
$date
	Thu Sep 09 13:34:49 2021
$end
$version
	Icarus Verilog
$end
$timescale
	1ps
$end
$scope module carryLookAhead_tb $end
$var wire 4 ! SUM [3:0] $end
$var wire 1 " COUT $end
$var reg 4 # A [3:0] $end
$var reg 4 $ B [3:0] $end
$var reg 1 % CIN $end
$scope module uut $end
$var wire 4 & a [3:0] $end
$var wire 4 ' b [3:0] $end
$var wire 1 ( c1 $end
$var wire 1 ) c2 $end
$var wire 1 * c3 $end
$var wire 1 + c4 $end
$var wire 1 % cin $end
$var wire 1 " cout $end
$var wire 4 , sum [3:0] $end
$var wire 4 - p [3:0] $end
$var wire 4 . g [3:0] $end
$upscope $end
$upscope $end
$enddefinitions $end
#0
$dumpvars
b0 .
b111 -
b1000 ,
0+
1*
1)
1(
b100 '
b11 &
1%
b100 $
b11 #
0"
b1000 !
$end
#10
b101 $
b101 '
b10 #
b10 &
#20
0*
0)
b11 !
b11 ,
1"
1+
b0 -
b1001 .
b1001 $
b1001 '
b1001 #
b1001 &
#30
1*
b1010 !
b1010 ,
1(
1)
b101 -
b1010 .
b1111 $
b1111 '
b1010 #
b1010 &
#35
0(
b1001 !
b1001 ,
0%
#45
0*
b111 !
b111 ,
0)
0"
0+
b111 -
b0 .
b100 $
b100 '
b11 #
b11 &
#55
b101 $
b101 '
b10 #
b10 &
#65
b10 !
b10 ,
1(
1"
1+
b0 -
b1001 .
b1001 $
b1001 '
b1001 #
b1001 &
#75
1*
b1001 !
b1001 ,
0(
1)
b101 -
b1010 .
b1111 $
b1111 '
b1010 #
b1010 &
