GateLvlModeling/Full_adder/Full_adder.v
// Code for full adder using gates
module full_adder(
    sum,c_out,a,b,c_in
);
input a,b,c_in;
output sum,c_out;

// intermediate values
wire s1; // sum value
wire c1,c2; // carry values
//Sum
xor(s1,a,b);
xor(sum,s1,c_in);
//Carry
and(c1,a,b);
and(c2,s1,c_in);
or(c_out,c2,c1);


endmodule

GateLvlModeling/Full_adder/fullAdder_tb.v
// Full adder test bench
`timescale 1ns/1ns
`include "Full_adder.v"

module fullAdder_tb;

reg a,b,c_in;
wire sum,c_out;

full_adder uut(sum,c_out,a,b,c_in);

initial begin
    $monitor($time,"Test Bench :A=%b , B=%b , CarryIN=%b , Sum=%b ,CarryOUT=%b",a,b,c_in,sum,c_out);
end

initial begin
    $dumpfile("full_adder.vcd");
    $dumpvars(0,fullAdder_tb);

    a = 1'b0; b = 1'b0; c_in = 1'b0;
    #5 a = 1'b0; b = 1'b0; c_in = 1'b1;
    #5 a = 1'b0; b = 1'b1; c_in = 1'b0;
    #5 a = 1'b0; b = 1'b1; c_in = 1'b1;
    #5 a = 1'b1; b = 1'b0; c_in = 1'b0;
    #5 a = 1'b1; b = 1'b0; c_in = 1'b1;
    #5 a = 1'b1; b = 1'b1; c_in = 1'b0;
    #5 a = 1'b1; b = 1'b1; c_in = 1'b1;

    #5 $display($time,"Test complete");

end

endmodule

GateLvlModeling/Full_adder/full_adder.vcd
$date
	Sat Aug 21 12:16:01 2021
$end
$version
	Icarus Verilog
$end
$timescale
	1ns
$end
$scope module fullAdder_tb $end
$var wire 1 ! sum $end
$var wire 1 " c_out $end
$var reg 1 # a $end
$var reg 1 $ b $end
$var reg 1 % c_in $end
$scope module uut $end
$var wire 1 # a $end
$var wire 1 $ b $end
$var wire 1 & c1 $end
$var wire 1 ' c2 $end
$var wire 1 % c_in $end
$var wire 1 " c_out $end
$var wire 1 ( s1 $end
$var wire 1 ! sum $end
$upscope $end
$upscope $end
$enddefinitions $end
#0
$dumpvars
0(
0'
0&
0%
0$
0#
0"
0!
$end
#5
1!
1%
#10
1(
0%
1$
#15
1"
0!
1'
1%
#20
0"
1!
0'
0%
0$
1#
#25
1"
0!
1'
1%
#30
0'
0(
1&
0%
1$
#35
1!
1%
