GateLvlModeling/Full_adder/Full_adder.v
// Code for full adder using gates
module full_adder(
    sum,c_out,a,b,c_in
);
input a,b,c_in;
output sum,c_out;

// intermediate values
wire s1; // sum value
wire c1,c2; // carry values
//Sum
xor(s1,a,b);
xor(sum,s1,c_in);
//Carry
and(c1,a,b);
and(c2,s1,c_in);
or(c_out,c2,c1);


endmodule

GateLvlModeling/4bit_FA/rippleAdder.v
// Riple carry adder: where the carry generated it sent to next block
// this code requires full adder module.

`include "../Full_adder/Full_adder.v"

module rippleAdder(out,cout,a,b,cin);

input [3:0]a,b;
// input [3:0]b;
output [3:0]out;
output cout;
input cin; // Initially set to 0 in TB;

wire c1,c2,c3;

//module full_adder(sum,c_out,a,b,c_in);
full_adder f0(out[0],c1,a[0],b[0],cin);
full_adder f1(out[1],c2,a[1],b[1],c1);
full_adder f2(out[2],c3,a[2],b[2],c2);
full_adder f3(out[3],cout,a[3],b[3],c3);

endmodule

GateLvlModeling/4bit_FA/rippleAdder_tb.v
`timescale 1ns/1ns
`include "rippleAdder.v"

module rippleAdder_tb();

reg [3:0]a,b;
// reg [3:0]b;
wire cout;
wire [3:0]out;
reg cin;

rippleAdder uut(out,cout,a,b,cin);

initial begin
    $dumpfile("RippleAdder.vcd");
    $dumpvars(0,rippleAdder_tb);
    $monitor($time,"\tCarryIn=%b\tA=%b\tB=%b\tOutput=%b\tCarry=%b",cin,a,b,out,cout);

    //carry in = 1
    cin = 1;
    a=4'd3; b=4'd4;
    #10 a=4'd2; b=4'd5;
    #10 a=4'd9; b=4'd9;
    #10 a=4'd10; b=4'd15;

    //Carry In = 1
    #5 cin = 0;
    #10 a=4'd3; b=4'd4;
    #10 a=4'd2; b=4'd5;
    #10 a=4'd9; b=4'd9;
    #10 a=4'd10; b=4'd15;

end

endmodule

GateLvlModeling/4bit_FA/RippleAdder.vcd
$date
	Sun Aug 22 17:26:27 2021
$end
$version
	Icarus Verilog
$end
$timescale
	1ns
$end
$scope module rippleAdder_tb $end
$var wire 4 ! out [3:0] $end
$var wire 1 " cout $end
$var reg 4 # a [3:0] $end
$var reg 4 $ b [3:0] $end
$var reg 1 % cin $end
$scope module uut $end
$var wire 4 & a [3:0] $end
$var wire 4 ' b [3:0] $end
$var wire 1 % cin $end
$var wire 4 ( out [3:0] $end
$var wire 1 " cout $end
$var wire 1 ) c3 $end
$var wire 1 * c2 $end
$var wire 1 + c1 $end
$scope module f0 $end
$var wire 1 , a $end
$var wire 1 - b $end
$var wire 1 . c1 $end
$var wire 1 / c2 $end
$var wire 1 % c_in $end
$var wire 1 + c_out $end
$var wire 1 0 s1 $end
$var wire 1 1 sum $end
$upscope $end
$scope module f1 $end
$var wire 1 2 a $end
$var wire 1 3 b $end
$var wire 1 4 c1 $end
$var wire 1 5 c2 $end
$var wire 1 + c_in $end
$var wire 1 * c_out $end
$var wire 1 6 s1 $end
$var wire 1 7 sum $end
$upscope $end
$scope module f2 $end
$var wire 1 8 a $end
$var wire 1 9 b $end
$var wire 1 : c1 $end
$var wire 1 ; c2 $end
$var wire 1 * c_in $end
$var wire 1 ) c_out $end
$var wire 1 < s1 $end
$var wire 1 = sum $end
$upscope $end
$scope module f3 $end
$var wire 1 > a $end
$var wire 1 ? b $end
$var wire 1 @ c1 $end
$var wire 1 A c2 $end
$var wire 1 ) c_in $end
$var wire 1 " c_out $end
$var wire 1 B s1 $end
$var wire 1 C sum $end
$upscope $end
$upscope $end
$upscope $end
$enddefinitions $end
#0
$dumpvars
1C
0B
0A
0@
0?
0>
0=
1<
1;
0:
19
08
07
16
15
04
03
12
01
10
1/
0.
0-
1,
1+
1*
1)
b1000 (
b100 '
b11 &
1%
b100 $
b11 #
0"
b1000 !
$end
#10
1-
0,
b101 $
b101 '
b10 #
b10 &
#20
0C
0)
0*
0=
0;
11
0/
b11 !
b11 (
17
05
1"
0<
00
1.
06
1@
09
1?
1,
02
1>
b1001 $
b1001 '
b1001 #
b1001 &
#30
1C
1)
17
1;
b1010 !
b1010 (
01
1/
1+
1*
1<
10
0.
14
13
19
0,
12
b1111 $
b1111 '
b1010 #
b1010 &
#35
07
0+
b1001 !
b1001 (
11
0/
0%
#45
0C
0)
1=
0;
b111 !
b111 (
17
0*
0"
16
04
0@
0-
03
0?
1,
0>
b100 $
b100 '
b11 #
b11 &
#55
1-
0,
b101 $
b101 '
b10 #
b10 &
#65
0=
01
1+
b10 !
b10 (
17
1"
0<
00
1.
06
1@
09
1?
1,
02
1>
b1001 $
b1001 '
b1001 #
b1001 &
#75
1C
1)
07
1;
b1001 !
b1001 (
11
0+
1*
1<
10
0.
14
13
19
0,
12
b1111 $
b1111 '
b1010 #
b1010 &
