BehavioralModelling/TrafficSignal/signalControl.v
`define TRUE 1'b1
`define FALSE 1'b0
`define RED 2'd0
`define YELLOW 2'd1
`define GREEN 2'd2

//States
`define S0 3'd0
`define S1 3'd1
`define S2 3'd2
`define S3 3'd3
`define S4 3'd4 

//Delays
`define Y2RDelay 3
`define R2GDelay 2

module signalControl(
    hwy,contry,flag,clock,clear
);

output [1:0] hwy,contry;
reg [1:0] hwy,contry;

input flag;

input clear,clock;

reg [2:0] state;
reg [2:0] nxt_state;

initial begin
    state = `S0;
    nxt_state = `S0;
    hwy = `GREEN;
    contry = `RED;
end

always @(posedge clock) begin
    state = nxt_state;
end

always @(state) begin
    case(state)
    `S0:begin
      hwy = `GREEN;
      contry = `RED;
    end
    `S1:begin
      hwy = `YELLOW;
      contry = `RED;
    end
    `S2:begin
      hwy = `RED;
      contry = `RED;
    end
    `S3:begin
      hwy = `RED;
      contry = `GREEN;
    end
    `S4:begin
      hwy = `RED;
      contry = `YELLOW;
    end    
    endcase
end

always @(state or clear or flag) begin
    if(clear)
        nxt_state = `S0;
    else 
        case(state)
        `S0: begin
                if(flag)
                    nxt_state = `S1;
                else 
                    nxt_state = `S0;
             end
        `S1: begin
                repeat (`Y2RDelay) @(posedge clock)
                    nxt_state = `S2;
             end
        `S2: begin
                repeat (`R2GDelay) @(posedge clock)
                    nxt_state = `S3;
             end
        `S3: begin
                if(flag)
                    nxt_state = `S3;
                else 
                    nxt_state = `S4;
             end
        `S4: begin
                repeat (`Y2RDelay) @(posedge clock)
                    nxt_state = `S0;
            end
        default: nxt_state = `S0;
        endcase
end
endmodule

BehavioralModelling/TrafficSignal/signalControl_tb.v
`timescale 1ps/1ps
`include "signalControl.v"

module signalControl_tb();

wire [1:0] main, cntry;
reg flag;
reg clock, clear;

signalControl uut(main,cntry,flag,clock,clear);

initial begin
    $dumpfile("Traffic.vcd");
    $dumpvars(0,signalControl_tb);
    $monitor($time,"\t Main=%b Contry =%b flag=%b",main,cntry,flag);
end

    initial begin
        clock = `FALSE;
        forever #10 clock = ~clock;
    end

    initial begin
        clear = `TRUE;
        repeat (5) @(negedge clock);
        clear = `FALSE;
    end

    initial begin
        flag = `FALSE;

        #200 flag = `TRUE;
        #100 flag = `FALSE;

        #200 flag = `TRUE;
        #100 flag = `FALSE;

        #200 flag = `TRUE;
        #100 flag = `FALSE;

        #100 $finish;

    end
endmodule

BehavioralModelling/TrafficSignal/Traffic.vcd
$date
	Mon Sep 13 12:26:35 2021
$end
$version
	Icarus Verilog
$end
$timescale
	1ps
$end
$scope module signalControl_tb $end
$var wire 2 ! main [1:0] $end
$var wire 2 " cntry [1:0] $end
$var reg 1 # clear $end
$var reg 1 $ clock $end
$var reg 1 % flag $end
$scope module uut $end
$var wire 1 # clear $end
$var wire 1 $ clock $end
$var wire 1 % flag $end
$var reg 2 & contry [1:0] $end
$var reg 2 ' hwy [1:0] $end
$var reg 3 ( nxt_state [2:0] $end
$var reg 3 ) state [2:0] $end
$upscope $end
$upscope $end
$enddefinitions $end
#0
$dumpvars
b0 )
b0 (
b10 '
b0 &
0%
0$
1#
b0 "
b10 !
$end
#10
1$
#20
0$
#30
1$
#40
0$
#50
1$
#60
0$
#70
1$
#80
0$
#90
1$
#100
0#
0$
#110
1$
#120
0$
#130
1$
#140
0$
#150
1$
#160
0$
#170
1$
#180
0$
#190
1$
#200
b1 (
0$
1%
#210
b1 !
b1 '
b1 )
1$
#220
0$
#230
b0 !
b0 '
b10 )
b10 (
1$
#240
0$
#250
1$
#260
0$
#270
1$
#280
0$
#290
1$
#300
0$
0%
#310
b10 "
b10 &
b11 )
b11 (
1$
#320
0$
#330
1$
#340
0$
#350
1$
#360
0$
#370
1$
#380
0$
#390
1$
#400
0$
#410
1$
#420
0$
#430
1$
#440
0$
#450
1$
#460
0$
#470
1$
#480
0$
#490
1$
#500
0$
1%
#510
1$
#520
0$
#530
1$
#540
0$
#550
1$
#560
0$
#570
1$
#580
0$
#590
1$
#600
b100 (
0$
0%
#610
b1 "
b1 &
b100 )
1$
#620
0$
#630
b0 "
b0 &
b10 !
b10 '
b0 )
b0 (
1$
#640
0$
#650
1$
#660
0$
#670
1$
#680
0$
#690
1$
#700
0$
#710
1$
#720
0$
#730
1$
#740
0$
#750
1$
#760
0$
#770
1$
#780
0$
#790
1$
#800
b1 (
0$
1%
#810
b1 !
b1 '
b1 )
1$
#820
0$
#830
b0 !
b0 '
b10 )
b10 (
1$
#840
0$
#850
1$
#860
0$
#870
1$
#880
0$
#890
1$
#900
0$
0%
#910
b10 "
b10 &
b11 )
b11 (
1$
