DataFlowModelling/FullAdder/fullAdder.v
module fullAdder(
    cout,sum,a,b,cin
);
    input [3:0]a,b;
    input cin;
    output [3:0]sum;
    output cout;

    assign {cout,sum} = a + b + cin;

endmodule

DataFlowModelling/FullAdder/fullAdder_tb.v
`timescale 1ps/1ps
`include "fullAdder.v"

module fullAdder_tb();

reg [3:0]a,b;
reg cin;
wire cout;
wire [3:0]sum;

fullAdder uut(cout,sum,a,b,cin);

initial begin
    $dumpfile("fullAdder.vcd");
    $dumpvars(0,fullAdder_tb);

    $monitor($time,"\tCin=%b,A=%b,B=%b,SUM=%b,Cout=%b",cin,a,b,sum,cout);

    //carry in = 1
    cin = 1;
    a=4'd3; b=4'd4;
    #10 a=4'd2; b=4'd5;
    #10 a=4'd9; b=4'd9;
    #10 a=4'd10; b=4'd15;

    //Carry In = 0
    #5 cin = 0;
    #10 a=4'd3; b=4'd4;
    #10 a=4'd2; b=4'd5;
    #10 a=4'd9; b=4'd9;
    #10 a=4'd10; b=4'd15;

end

endmodule

DataFlowModelling/FullAdder/fullAdder.vcd
$date
	Thu Sep 09 12:14:53 2021
$end
$version
	Icarus Verilog
$end
$timescale
	1ps
$end
$scope module fullAdder_tb $end
$var wire 4 ! sum [3:0] $end
$var wire 1 " cout $end
$var reg 4 # a [3:0] $end
$var reg 4 $ b [3:0] $end
$var reg 1 % cin $end
$scope module uut $end
$var wire 4 & a [3:0] $end
$var wire 4 ' b [3:0] $end
$var wire 1 % cin $end
$var wire 4 ( sum [3:0] $end
$var wire 1 " cout $end
$upscope $end
$upscope $end
$enddefinitions $end
#0
$dumpvars
b1000 (
b100 '
b11 &
1%
b100 $
b11 #
0"
b1000 !
$end
#10
b101 $
b101 '
b10 #
b10 &
#20
1"
b11 !
b11 (
b1001 $
b1001 '
b1001 #
b1001 &
#30
b1010 !
b1010 (
b1111 $
b1111 '
b1010 #
b1010 &
#35
b1001 !
b1001 (
0%
#45
0"
b111 !
b111 (
b100 $
b100 '
b11 #
b11 &
#55
b101 $
b101 '
b10 #
b10 &
#65
1"
b10 !
b10 (
b1001 $
b1001 '
b1001 #
b1001 &
#75
b1001 !
b1001 (
b1111 $
b1111 '
b1010 #
b1010 &
