BehavioralModelling/Counter/counter.v
module counter(
    q,clock,clear
);

input clock,clear;
output [3:0]q;
reg [3:0]q;

always @(negedge clock or posedge clear) begin
    if(clear)
        q = 4'd0;
    else 
        q = (q+1) % 16;
end

endmodule

BehavioralModelling/Counter/counter_tb.v
`timescale 1ps/1ps
`include "counter.v"

module counter_tb();

reg clock,clear;
wire [3:0]q;

counter uut(q,clock,clear);

initial begin
    $dumpfile("Counter.vcd");
    $dumpvars(0,counter_tb);
    $monitor($time,"\tCount=%b\tClock=%b\tclear=%b",q,clock,clear);

    clear = 1'b1;
    #10 clear =1'b0; 
    #80 clear =1'b1; 
    #20 clear =1'b0;
end

initial begin
    clock = 1'b0;
    forever #10 clock=~clock;
end

initial begin
     #200 $finish;
end

endmodule

BehavioralModelling/Counter/Counter.vcd
$date
	Sun Sep 12 14:54:32 2021
$end
$version
	Icarus Verilog
$end
$timescale
	1ps
$end
$scope module counter_tb $end
$var wire 4 ! q [3:0] $end
$var reg 1 " clear $end
$var reg 1 # clock $end
$scope module uut $end
$var wire 1 " clear $end
$var wire 1 # clock $end
$var reg 4 $ q [3:0] $end
$upscope $end
$upscope $end
$enddefinitions $end
#0
$dumpvars
b0 $
0#
1"
b0 !
$end
#10
1#
0"
#20
b1 !
b1 $
0#
#30
1#
#40
b10 !
b10 $
0#
#50
1#
#60
b11 !
b11 $
0#
#70
1#
#80
b100 !
b100 $
0#
#90
b0 !
b0 $
1#
1"
#100
0#
#110
1#
0"
#120
b1 !
b1 $
0#
#130
1#
#140
b10 !
b10 $
0#
#150
1#
#160
b11 !
b11 $
0#
#170
1#
#180
b100 !
b100 $
0#
#190
1#
#200
b101 !
b101 $
0#
