DataFlowModelling/RippleCounter/dff.v
module dff(
    q,qb,d,clock,clear
);

output q,qb;
input d,clock,clear;

wire s,sb,r,rb,cb;

assign cb = ~clear;

assign sb = ~(rb & s),s= ~(sb & cb & ~clock),r= ~(rb & ~clock & s),rb= ~(r & cb & d);

assign q = ~(s & qb), qb = ~(q & r & cb);


endmodule

DataFlowModelling/RippleCounter/tff.v
`include "dff.v"
module tff(
    q,clock,clear
);

output q;
input clock,clear;

dff ff1(q, , ~q, clock, clear);

endmodule

DataFlowModelling/RippleCounter/RipCounter.v
`include "tff.v"

module Ripplecounter(
    q,clock,clear
);

 output [3:0]q;
 input clock,clear;

tff t1(q[0],clock,clear);
tff t2(q[1],q[0],clear);
tff t3(q[2],q[1],clear);
tff t4(q[3],q[2],clear);

endmodule

// module tff(
//     q,clock,clear
// );

// input clock,clear;
// output q;

// dff ff1(q,,~q,clk,clear);

// endmodule

// module dff(
//     q,qb,d,clk,clear
// );

// output q,qb;
// input d,clk,clear;

// wire s,sb,r,rb,cb;

// assign cb = ~clear;

// assign sb = ~(rb & s), s= ~(sb & cb & ~clk),r= ~(rb & ~clk & s),rb= ~(r &cb & d);

// assign q = ~(s & qb), qb = ~(q & r & cb);


// endmodule

DataFlowModelling/RippleCounter/RipCounter_tb.v
`timescale 1ps/1ps
`include "RipCounter.v"

module ripcounter_tb();

reg clear,clock;
wire [3:0]out;

Ripplecounter uut(out, clock, clear);

initial begin
    $dumpfile("RippleCounter.vcd");
    $dumpvars(0,ripcounter_tb);
    $monitor($time,"\tOut:%b,\tClear:%b\t",out,clear);
    // $display($time,"\tOut:%b,\tClock:%b,\tClear:%b\t",out,clock,clear);
    clear = 1'b1;
    #34 clear = 1'b0;
    #200 clear = 1'b1;
    #50 clear = 1'b0;
end

initial begin
    clock = 1'b0;
    forever #10 clock = ~clock;
end

initial begin
    #400 $finish;
end

endmodule

DataFlowModelling/RippleCounter/RippleCounter.vcd
$date
	Thu Sep 09 18:22:43 2021
$end
$version
	Icarus Verilog
$end
$timescale
	1ps
$end
$scope module ripcounter_tb $end
$var wire 4 ! out [3:0] $end
$var reg 1 " clear $end
$var reg 1 # clock $end
$scope module uut $end
$var wire 1 " clear $end
$var wire 1 # clock $end
$var wire 4 $ q [3:0] $end
$scope module t1 $end
$var wire 1 " clear $end
$var wire 1 # clock $end
$var wire 1 % q $end
$scope module ff1 $end
$var wire 1 & cb $end
$var wire 1 " clear $end
$var wire 1 # clock $end
$var wire 1 ' d $end
$var wire 1 % q $end
$var wire 1 ( qb $end
$var wire 1 ) r $end
$var wire 1 * rb $end
$var wire 1 + s $end
$var wire 1 , sb $end
$upscope $end
$upscope $end
$scope module t2 $end
$var wire 1 " clear $end
$var wire 1 - clock $end
$var wire 1 . q $end
$scope module ff1 $end
$var wire 1 / cb $end
$var wire 1 " clear $end
$var wire 1 - clock $end
$var wire 1 0 d $end
$var wire 1 . q $end
$var wire 1 1 qb $end
$var wire 1 2 r $end
$var wire 1 3 rb $end
$var wire 1 4 s $end
$var wire 1 5 sb $end
$upscope $end
$upscope $end
$scope module t3 $end
$var wire 1 " clear $end
$var wire 1 6 clock $end
$var wire 1 7 q $end
$scope module ff1 $end
$var wire 1 8 cb $end
$var wire 1 " clear $end
$var wire 1 6 clock $end
$var wire 1 9 d $end
$var wire 1 7 q $end
$var wire 1 : qb $end
$var wire 1 ; r $end
$var wire 1 < rb $end
$var wire 1 = s $end
$var wire 1 > sb $end
$upscope $end
$upscope $end
$scope module t4 $end
$var wire 1 " clear $end
$var wire 1 ? clock $end
$var wire 1 @ q $end
$scope module ff1 $end
$var wire 1 A cb $end
$var wire 1 " clear $end
$var wire 1 ? clock $end
$var wire 1 B d $end
$var wire 1 @ q $end
$var wire 1 C qb $end
$var wire 1 D r $end
$var wire 1 E rb $end
$var wire 1 F s $end
$var wire 1 G sb $end
$upscope $end
$upscope $end
$upscope $end
$upscope $end
$enddefinitions $end
#0
$dumpvars
0G
1F
1E
0D
1C
1B
0A
0@
0?
0>
1=
1<
0;
1:
19
08
07
06
05
14
13
02
11
10
0/
0.
0-
0,
1+
1*
0)
1(
1'
0&
0%
b0 $
0#
1"
b0 !
$end
#10
1)
1#
#20
0)
0#
#30
1)
1#
#34
1,
0*
1&
1/
18
1A
0"
#40
15
03
12
0(
1*
0'
1-
b1 !
b1 $
1%
0+
0#
#50
0,
1+
1#
#60
1>
0<
1;
01
13
00
16
1.
04
1'
0-
b10 !
b10 $
0%
1(
0)
0#
#70
1,
0*
1)
1#
#80
05
14
0(
1*
0'
1-
b11 !
b11 $
1%
0+
0#
#90
0,
1+
1#
#100
1G
0E
1D
0:
1<
09
1?
17
0=
10
06
0.
11
02
1'
0-
b100 !
b100 $
0%
1(
0)
0#
#110
1,
0*
1)
1#
#120
15
03
12
0(
1*
0'
1-
b101 !
b101 $
1%
0+
0#
#130
0,
1+
1#
#140
0>
1=
01
13
00
16
1.
04
1'
0-
b110 !
b110 $
0%
1(
0)
0#
#150
1,
0*
1)
1#
#160
05
14
0(
1*
0'
1-
b111 !
b111 $
1%
0+
0#
#170
0,
1+
1#
#180
0C
1E
0B
1@
0F
19
0?
07
1:
0;
10
06
0.
11
02
1'
0-
b1000 !
b1000 $
0%
1(
0)
0#
#190
1,
0*
1)
1#
#200
15
03
12
0(
1*
0'
1-
b1001 !
b1001 $
1%
0+
0#
#210
0,
1+
1#
#220
1>
0<
1;
01
13
00
16
1.
04
1'
0-
b1010 !
b1010 $
0%
1(
0)
0#
#230
1,
0*
1)
1#
#234
0;
10
06
1B
0,
02
0.
05
0>
0D
b0 !
b0 $
0@
0G
1*
14
1<
1F
11
1C
0&
0/
08
0A
1"
#240
0)
0#
#250
1)
1#
#260
0)
0#
#270
1)
1#
#280
0)
0#
#284
1&
1/
18
1A
0"
#290
1,
0*
1)
1#
#300
15
03
12
0(
1*
0'
1-
b1 !
b1 $
1%
0+
0#
#310
0,
1+
1#
#320
1>
0<
1;
01
13
00
16
1.
04
1'
0-
b10 !
b10 $
0%
1(
0)
0#
#330
1,
0*
1)
1#
#340
05
14
0(
1*
0'
1-
b11 !
b11 $
1%
0+
0#
#350
0,
1+
1#
#360
1G
0E
1D
0:
1<
09
1?
17
0=
10
06
0.
11
02
1'
0-
b100 !
b100 $
0%
1(
0)
0#
#370
1,
0*
1)
1#
#380
15
03
12
0(
1*
0'
1-
b101 !
b101 $
1%
0+
0#
#390
0,
1+
1#
#400
0>
1=
01
13
00
16
1.
04
1'
0-
b110 !
b110 $
0%
1(
0)
0#
