SwitchLevel/flipflop/not.v
module notgate(out,in);
    
    input in;
    output out;

    supply1 vcc;
    supply0 gnd;

    pmos (out,vcc,in);
    nmos (out,gnd,in);

endmodule

SwitchLevel/flipflop/ff.v
`include "not.v"

module ff(
    q,qbar,d,clk
);
    input d,clk;
    output q,qbar;

    wire e;

    notgate n1(nclk,clk);

    cmos (e,d,clk,nclk);
    cmos (e,~qbar,nclk,clk);

    notgate n2(qbar,e);
    notgate n3(q,~e);



endmodule

SwitchLevel/flipflop/ff_tb.v
`timescale 1ps/1ps
`include "ff.v"

module ff_tb();
    
    reg d,clk;
    wire q,qbar;

    ff uut(q,qbar,d,clk);

    initial begin
        $dumpfile("ff.vcd");
        $dumpvars(0,ff_tb);
        $monitor($time,"\tq=%b\tqb=%b\td=%b\tclk=%b",q,qbar,d,clk);

        d = 1'b1;
        forever #20 d = ~d;
    end
    
    initial begin
        clk = 1'b0;
        forever #10 clk = ~clk;
    end

    initial begin
        #100 $finish;
    end

endmodule

SwitchLevel/flipflop/ff.vcd
$date
	Thu Sep 16 14:47:36 2021
$end
$version
	Icarus Verilog
$end
$timescale
	1ps
$end
$scope module ff_tb $end
$var wire 1 ! q $end
$var wire 1 " qbar $end
$var reg 1 # clk $end
$var reg 1 $ d $end
$scope module uut $end
$var wire 1 # clk $end
$var wire 1 $ d $end
$var wire 1 % e $end
$var wire 1 & nclk $end
$var wire 1 ! q $end
$var wire 1 " qbar $end
$scope module n1 $end
$var wire 1 ' gnd $end
$var wire 1 # in $end
$var wire 1 & out $end
$var wire 1 ( vcc $end
$upscope $end
$scope module n2 $end
$var wire 1 ) gnd $end
$var wire 1 % in $end
$var wire 1 " out $end
$var wire 1 * vcc $end
$upscope $end
$scope module n3 $end
$var wire 1 + gnd $end
$var wire 1 , in $end
$var wire 1 ! out $end
$var wire 1 - vcc $end
$upscope $end
$upscope $end
$upscope $end
$enddefinitions $end
#0
$dumpvars
1-
x,
0+
1*
0)
1(
0'
1&
x%
1$
0#
x"
x!
$end
#10
1!
0,
0"
1%
0&
1#
#20
1&
0#
0"
1%
0$
#30
0!
1,
1"
0%
0&
1#
#40
1&
0#
1"
0%
1$
#50
1!
0,
0"
1%
0&
1#
#60
1&
0#
0"
1%
0$
#70
0!
1,
1"
0%
0&
1#
#80
1&
0#
1"
0%
1$
#90
1!
0,
0"
1%
0&
1#
#100
1&
0#
0"
1%
0$
